transformers-stubs/__init__.pyi
transformers-stubs/activations.pyi
transformers-stubs/activations_tf.pyi
transformers-stubs/audio_utils.pyi
transformers-stubs/cache_utils.pyi
transformers-stubs/configuration_utils.pyi
transformers-stubs/convert_graph_to_onnx.pyi
transformers-stubs/convert_pytorch_checkpoint_to_tf2.pyi
transformers-stubs/convert_slow_tokenizer.pyi
transformers-stubs/convert_slow_tokenizers_checkpoints_to_fast.pyi
transformers-stubs/convert_tf_hub_seq_to_seq_bert_to_pytorch.pyi
transformers-stubs/debug_utils.pyi
transformers-stubs/dependency_versions_check.pyi
transformers-stubs/dependency_versions_table.pyi
transformers-stubs/dynamic_module_utils.pyi
transformers-stubs/feature_extraction_sequence_utils.pyi
transformers-stubs/feature_extraction_utils.pyi
transformers-stubs/file_utils.pyi
transformers-stubs/hf_argparser.pyi
transformers-stubs/hyperparameter_search.pyi
transformers-stubs/image_processing_base.pyi
transformers-stubs/image_processing_utils.pyi
transformers-stubs/image_processing_utils_fast.pyi
transformers-stubs/image_transforms.pyi
transformers-stubs/image_utils.pyi
transformers-stubs/keras_callbacks.pyi
transformers-stubs/model_debugging_utils.pyi
transformers-stubs/modelcard.pyi
transformers-stubs/modeling_attn_mask_utils.pyi
transformers-stubs/modeling_flash_attention_utils.pyi
transformers-stubs/modeling_flax_outputs.pyi
transformers-stubs/modeling_flax_pytorch_utils.pyi
transformers-stubs/modeling_flax_utils.pyi
transformers-stubs/modeling_gguf_pytorch_utils.pyi
transformers-stubs/modeling_outputs.pyi
transformers-stubs/modeling_rope_utils.pyi
transformers-stubs/modeling_tf_outputs.pyi
transformers-stubs/modeling_tf_pytorch_utils.pyi
transformers-stubs/modeling_tf_utils.pyi
transformers-stubs/modeling_utils.pyi
transformers-stubs/optimization.pyi
transformers-stubs/optimization_tf.pyi
transformers-stubs/processing_utils.pyi
transformers-stubs/pytorch_utils.pyi
transformers-stubs/safetensors_conversion.pyi
types_transformers-0.1.0.dist-info/METADATA
types_transformers-0.1.0.dist-info/WHEEL
types_transformers-0.1.0.dist-info/top_level.txt
types_transformers-0.1.0.dist-info/RECORD
